[
  { "inputs": [], "stateMutability": "nonpayable", "type": "constructor" },
  { "inputs": [], "name": "AccessControlBadConfirmation", "type": "error" },
  {
    "inputs": [
      { "internalType": "address", "name": "account", "type": "address" },
      { "internalType": "bytes32", "name": "neededRole", "type": "bytes32" }
    ],
    "name": "AccessControlUnauthorizedAccount",
    "type": "error"
  },
  { "inputs": [], "name": "InvalidInitialization", "type": "error" },
  { "inputs": [], "name": "NotInitializing", "type": "error" },
  {
    "inputs": [
      { "internalType": "address", "name": "owner", "type": "address" }
    ],
    "name": "OwnableInvalidOwner",
    "type": "error"
  },
  {
    "inputs": [
      { "internalType": "address", "name": "account", "type": "address" }
    ],
    "name": "OwnableUnauthorizedAccount",
    "type": "error"
  },
  {
    "anonymous": false,
    "inputs": [
      {
        "indexed": true,
        "internalType": "uint256",
        "name": "roundId",
        "type": "uint256"
      },
      {
        "indexed": false,
        "internalType": "address",
        "name": "recipient",
        "type": "address"
      },
      {
        "indexed": false,
        "internalType": "uint256",
        "name": "articleId",
        "type": "uint256"
      },
      {
        "indexed": false,
        "internalType": "uint256",
        "name": "amount",
        "type": "uint256"
      }
    ],
    "name": "Allocated",
    "type": "event"
  },
  {
    "anonymous": false,
    "inputs": [
      {
        "indexed": true,
        "internalType": "address",
        "name": "author",
        "type": "address"
      },
      {
        "indexed": true,
        "internalType": "address",
        "name": "from",
        "type": "address"
      },
      {
        "indexed": false,
        "internalType": "uint256",
        "name": "articleId",
        "type": "uint256"
      },
      {
        "indexed": false,
        "internalType": "uint256",
        "name": "amount",
        "type": "uint256"
      }
    ],
    "name": "ArticleDonated",
    "type": "event"
  },
  {
    "anonymous": false,
    "inputs": [
      {
        "indexed": true,
        "internalType": "address",
        "name": "author",
        "type": "address"
      },
      {
        "indexed": false,
        "internalType": "string",
        "name": "content",
        "type": "string"
      },
      {
        "indexed": false,
        "internalType": "uint256",
        "name": "articleId",
        "type": "uint256"
      }
    ],
    "name": "ArticlePosted",
    "type": "event"
  },
  {
    "anonymous": false,
    "inputs": [
      {
        "indexed": false,
        "internalType": "uint64",
        "name": "version",
        "type": "uint64"
      }
    ],
    "name": "Initialized",
    "type": "event"
  },
  {
    "anonymous": false,
    "inputs": [
      {
        "indexed": true,
        "internalType": "address",
        "name": "previousOwner",
        "type": "address"
      },
      {
        "indexed": true,
        "internalType": "address",
        "name": "newOwner",
        "type": "address"
      }
    ],
    "name": "OwnershipTransferred",
    "type": "event"
  },
  {
    "anonymous": false,
    "inputs": [
      {
        "indexed": true,
        "internalType": "bytes32",
        "name": "role",
        "type": "bytes32"
      },
      {
        "indexed": true,
        "internalType": "bytes32",
        "name": "previousAdminRole",
        "type": "bytes32"
      },
      {
        "indexed": true,
        "internalType": "bytes32",
        "name": "newAdminRole",
        "type": "bytes32"
      }
    ],
    "name": "RoleAdminChanged",
    "type": "event"
  },
  {
    "anonymous": false,
    "inputs": [
      {
        "indexed": true,
        "internalType": "bytes32",
        "name": "role",
        "type": "bytes32"
      },
      {
        "indexed": true,
        "internalType": "address",
        "name": "account",
        "type": "address"
      },
      {
        "indexed": true,
        "internalType": "address",
        "name": "sender",
        "type": "address"
      }
    ],
    "name": "RoleGranted",
    "type": "event"
  },
  {
    "anonymous": false,
    "inputs": [
      {
        "indexed": true,
        "internalType": "bytes32",
        "name": "role",
        "type": "bytes32"
      },
      {
        "indexed": true,
        "internalType": "address",
        "name": "account",
        "type": "address"
      },
      {
        "indexed": true,
        "internalType": "address",
        "name": "sender",
        "type": "address"
      }
    ],
    "name": "RoleRevoked",
    "type": "event"
  },
  {
    "anonymous": false,
    "inputs": [
      {
        "indexed": true,
        "internalType": "address",
        "name": "author",
        "type": "address"
      },
      {
        "indexed": false,
        "internalType": "uint256",
        "name": "articleId",
        "type": "uint256"
      },
      {
        "indexed": false,
        "internalType": "uint256",
        "name": "roundId",
        "type": "uint256"
      }
    ],
    "name": "RoundApplied",
    "type": "event"
  },
  {
    "anonymous": false,
    "inputs": [
      {
        "indexed": true,
        "internalType": "address",
        "name": "owner",
        "type": "address"
      },
      {
        "indexed": false,
        "internalType": "address",
        "name": "ipoolAddress",
        "type": "address"
      },
      {
        "indexed": false,
        "internalType": "uint256",
        "name": "roundId",
        "type": "uint256"
      },
      {
        "indexed": false,
        "internalType": "bytes",
        "name": "name",
        "type": "bytes"
      },
      {
        "indexed": false,
        "internalType": "bytes",
        "name": "description",
        "type": "bytes"
      },
      {
        "indexed": false,
        "internalType": "uint256",
        "name": "startDate",
        "type": "uint256"
      },
      {
        "indexed": false,
        "internalType": "uint256",
        "name": "endDate",
        "type": "uint256"
      }
    ],
    "name": "RoundCreated",
    "type": "event"
  },
  {
    "inputs": [
      { "internalType": "uint256", "name": "_roundId", "type": "uint256" }
    ],
    "name": "Allocate",
    "outputs": [],
    "stateMutability": "nonpayable",
    "type": "function"
  },
  {
    "inputs": [],
    "name": "DEFAULT_ADMIN_ROLE",
    "outputs": [{ "internalType": "bytes32", "name": "", "type": "bytes32" }],
    "stateMutability": "view",
    "type": "function"
  },
  {
    "inputs": [
      { "internalType": "uint256", "name": "_roundId", "type": "uint256" },
      { "internalType": "address", "name": "_author", "type": "address" },
      { "internalType": "uint256", "name": "_articleId", "type": "uint256" }
    ],
    "name": "acceptApplication",
    "outputs": [],
    "stateMutability": "nonpayable",
    "type": "function"
  },
  {
    "inputs": [
      { "internalType": "uint256", "name": "_roundId", "type": "uint256" }
    ],
    "name": "activateRound",
    "outputs": [],
    "stateMutability": "nonpayable",
    "type": "function"
  },
  {
    "inputs": [
      { "internalType": "address", "name": "_admin", "type": "address" }
    ],
    "name": "addAdmin",
    "outputs": [],
    "stateMutability": "nonpayable",
    "type": "function"
  },
  {
    "inputs": [
      { "internalType": "uint256", "name": "_roundId", "type": "uint256" },
      { "internalType": "uint256", "name": "_articleId", "type": "uint256" }
    ],
    "name": "applyForRound",
    "outputs": [],
    "stateMutability": "nonpayable",
    "type": "function"
  },
  {
    "inputs": [
      { "internalType": "uint256", "name": "_amount", "type": "uint256" }
    ],
    "name": "changeMinimumAmount",
    "outputs": [],
    "stateMutability": "nonpayable",
    "type": "function"
  },
  {
    "inputs": [
      { "internalType": "address", "name": "_admin", "type": "address" }
    ],
    "name": "checkAdminRole",
    "outputs": [{ "internalType": "bool", "name": "", "type": "bool" }],
    "stateMutability": "view",
    "type": "function"
  },
  {
    "inputs": [
      { "internalType": "address", "name": "_sender", "type": "address" },
      { "internalType": "address", "name": "_author", "type": "address" },
      { "internalType": "uint256", "name": "_articleId", "type": "uint256" }
    ],
    "name": "checkOwner",
    "outputs": [{ "internalType": "bool", "name": "", "type": "bool" }],
    "stateMutability": "view",
    "type": "function"
  },
  {
    "inputs": [
      { "internalType": "bytes32", "name": "uid", "type": "bytes32" },
      { "internalType": "address", "name": "recipient", "type": "address" },
      { "internalType": "uint256", "name": "score", "type": "uint256" }
    ],
    "name": "checkScore",
    "outputs": [{ "internalType": "bool", "name": "", "type": "bool" }],
    "stateMutability": "view",
    "type": "function"
  },
  {
    "inputs": [
      { "internalType": "string", "name": "_name", "type": "string" },
      { "internalType": "string", "name": "_description", "type": "string" },
      { "internalType": "uint256", "name": "_startDate", "type": "uint256" },
      { "internalType": "uint256", "name": "_endDate", "type": "uint256" }
    ],
    "name": "createRound",
    "outputs": [],
    "stateMutability": "nonpayable",
    "type": "function"
  },
  {
    "inputs": [
      { "internalType": "uint256", "name": "_roundId", "type": "uint256" }
    ],
    "name": "deactivateRound",
    "outputs": [],
    "stateMutability": "nonpayable",
    "type": "function"
  },
  {
    "inputs": [
      { "internalType": "uint256", "name": "_roundId", "type": "uint256" },
      { "internalType": "address", "name": "_author", "type": "address" },
      { "internalType": "uint256", "name": "_articleId", "type": "uint256" }
    ],
    "name": "denyApplication",
    "outputs": [],
    "stateMutability": "nonpayable",
    "type": "function"
  },
  {
    "inputs": [
      { "internalType": "uint256", "name": "_roundId", "type": "uint256" }
    ],
    "name": "deposit",
    "outputs": [{ "internalType": "bool", "name": "", "type": "bool" }],
    "stateMutability": "payable",
    "type": "function"
  },
  {
    "inputs": [
      {
        "internalType": "address payable",
        "name": "_author",
        "type": "address"
      },
      { "internalType": "uint256", "name": "_articleId", "type": "uint256" }
    ],
    "name": "donateToArticle",
    "outputs": [],
    "stateMutability": "payable",
    "type": "function"
  },
  {
    "inputs": [],
    "name": "eas",
    "outputs": [
      { "internalType": "contract IEAS", "name": "", "type": "address" }
    ],
    "stateMutability": "view",
    "type": "function"
  },
  {
    "inputs": [
      { "internalType": "address", "name": "_author", "type": "address" }
    ],
    "name": "getAllAuthorArticle",
    "outputs": [
      {
        "components": [
          { "internalType": "uint256", "name": "id", "type": "uint256" },
          {
            "internalType": "address payable",
            "name": "author",
            "type": "address"
          },
          { "internalType": "string", "name": "content", "type": "string" },
          {
            "internalType": "uint256",
            "name": "donationsReceived",
            "type": "uint256"
          }
        ],
        "internalType": "struct IPledgePost.Article[]",
        "name": "",
        "type": "tuple[]"
      }
    ],
    "stateMutability": "view",
    "type": "function"
  },
  {
    "inputs": [
      { "internalType": "uint256", "name": "_roundId", "type": "uint256" },
      { "internalType": "address", "name": "_author", "type": "address" },
      { "internalType": "uint256", "name": "_articleId", "type": "uint256" }
    ],
    "name": "getAllocation",
    "outputs": [{ "internalType": "uint256", "name": "", "type": "uint256" }],
    "stateMutability": "view",
    "type": "function"
  },
  {
    "inputs": [
      { "internalType": "uint256", "name": "_roundId", "type": "uint256" },
      { "internalType": "address", "name": "_author", "type": "address" },
      { "internalType": "uint256", "name": "_articleId", "type": "uint256" }
    ],
    "name": "getApplicationStatus",
    "outputs": [
      {
        "internalType": "enum IPledgePost.ApplicationStatus",
        "name": "",
        "type": "uint8"
      }
    ],
    "stateMutability": "view",
    "type": "function"
  },
  {
    "inputs": [
      { "internalType": "uint256", "name": "_roundId", "type": "uint256" },
      { "internalType": "uint256", "name": "_index", "type": "uint256" }
    ],
    "name": "getAppliedArticle",
    "outputs": [
      {
        "components": [
          { "internalType": "uint256", "name": "id", "type": "uint256" },
          {
            "internalType": "address payable",
            "name": "author",
            "type": "address"
          },
          { "internalType": "string", "name": "content", "type": "string" },
          {
            "internalType": "uint256",
            "name": "donationsReceived",
            "type": "uint256"
          }
        ],
        "internalType": "struct IPledgePost.Article",
        "name": "",
        "type": "tuple"
      }
    ],
    "stateMutability": "view",
    "type": "function"
  },
  {
    "inputs": [
      { "internalType": "address", "name": "_author", "type": "address" },
      { "internalType": "uint256", "name": "_articleId", "type": "uint256" }
    ],
    "name": "getAppliedRound",
    "outputs": [
      {
        "components": [
          { "internalType": "uint256", "name": "id", "type": "uint256" },
          { "internalType": "address", "name": "owner", "type": "address" },
          { "internalType": "bytes", "name": "name", "type": "bytes" },
          { "internalType": "bytes", "name": "description", "type": "bytes" },
          {
            "internalType": "address payable",
            "name": "poolAddress",
            "type": "address"
          },
          {
            "internalType": "uint256",
            "name": "poolAmount",
            "type": "uint256"
          },
          { "internalType": "uint256", "name": "startDate", "type": "uint256" },
          { "internalType": "uint256", "name": "endDate", "type": "uint256" },
          { "internalType": "bool", "name": "isActive", "type": "bool" }
        ],
        "internalType": "struct IPledgePost.Round",
        "name": "",
        "type": "tuple"
      }
    ],
    "stateMutability": "view",
    "type": "function"
  },
  {
    "inputs": [
      { "internalType": "address", "name": "_author", "type": "address" },
      { "internalType": "uint256", "name": "_articleId", "type": "uint256" }
    ],
    "name": "getArticleDonators",
    "outputs": [
      { "internalType": "address[]", "name": "", "type": "address[]" }
    ],
    "stateMutability": "view",
    "type": "function"
  },
  {
    "inputs": [
      { "internalType": "address", "name": "_author", "type": "address" },
      { "internalType": "uint256", "name": "_articleId", "type": "uint256" }
    ],
    "name": "getAuthorArticle",
    "outputs": [
      {
        "components": [
          { "internalType": "uint256", "name": "id", "type": "uint256" },
          {
            "internalType": "address payable",
            "name": "author",
            "type": "address"
          },
          { "internalType": "string", "name": "content", "type": "string" },
          {
            "internalType": "uint256",
            "name": "donationsReceived",
            "type": "uint256"
          }
        ],
        "internalType": "struct IPledgePost.Article",
        "name": "",
        "type": "tuple"
      }
    ],
    "stateMutability": "view",
    "type": "function"
  },
  {
    "inputs": [
      { "internalType": "address", "name": "_author", "type": "address" },
      { "internalType": "uint256", "name": "_articleId", "type": "uint256" }
    ],
    "name": "getDonatedAmount",
    "outputs": [{ "internalType": "uint256", "name": "", "type": "uint256" }],
    "stateMutability": "view",
    "type": "function"
  },
  {
    "inputs": [
      { "internalType": "uint256", "name": "_roundId", "type": "uint256" },
      { "internalType": "address", "name": "_author", "type": "address" },
      { "internalType": "uint256", "name": "_articleId", "type": "uint256" }
    ],
    "name": "getMatchingAmount",
    "outputs": [{ "internalType": "uint256", "name": "", "type": "uint256" }],
    "stateMutability": "view",
    "type": "function"
  },
  {
    "inputs": [
      { "internalType": "bytes32", "name": "uid", "type": "bytes32" },
      { "internalType": "address", "name": "recipient", "type": "address" }
    ],
    "name": "getPassportAttestation",
    "outputs": [
      { "internalType": "uint256", "name": "score", "type": "uint256" }
    ],
    "stateMutability": "view",
    "type": "function"
  },
  {
    "inputs": [
      { "internalType": "bytes32", "name": "role", "type": "bytes32" }
    ],
    "name": "getRoleAdmin",
    "outputs": [{ "internalType": "bytes32", "name": "", "type": "bytes32" }],
    "stateMutability": "view",
    "type": "function"
  },
  {
    "inputs": [
      { "internalType": "uint256", "name": "_roundId", "type": "uint256" }
    ],
    "name": "getRound",
    "outputs": [
      {
        "components": [
          { "internalType": "uint256", "name": "id", "type": "uint256" },
          { "internalType": "address", "name": "owner", "type": "address" },
          { "internalType": "bytes", "name": "name", "type": "bytes" },
          { "internalType": "bytes", "name": "description", "type": "bytes" },
          {
            "internalType": "address payable",
            "name": "poolAddress",
            "type": "address"
          },
          {
            "internalType": "uint256",
            "name": "poolAmount",
            "type": "uint256"
          },
          { "internalType": "uint256", "name": "startDate", "type": "uint256" },
          { "internalType": "uint256", "name": "endDate", "type": "uint256" },
          { "internalType": "bool", "name": "isActive", "type": "bool" }
        ],
        "internalType": "struct IPledgePost.Round",
        "name": "",
        "type": "tuple"
      }
    ],
    "stateMutability": "view",
    "type": "function"
  },
  {
    "inputs": [],
    "name": "getRoundLength",
    "outputs": [{ "internalType": "uint256", "name": "", "type": "uint256" }],
    "stateMutability": "view",
    "type": "function"
  },
  {
    "inputs": [
      { "internalType": "address", "name": "_author", "type": "address" },
      { "internalType": "uint256", "name": "_articleId", "type": "uint256" },
      { "internalType": "uint256", "name": "_roundId", "type": "uint256" }
    ],
    "name": "getSqrtSumRoundDonation",
    "outputs": [{ "internalType": "uint256", "name": "", "type": "uint256" }],
    "stateMutability": "view",
    "type": "function"
  },
  {
    "inputs": [{ "internalType": "uint256", "name": "x", "type": "uint256" }],
    "name": "getSquareRoot",
    "outputs": [{ "internalType": "uint256", "name": "", "type": "uint256" }],
    "stateMutability": "pure",
    "type": "function"
  },
  {
    "inputs": [
      { "internalType": "uint256", "name": "_roundId", "type": "uint256" }
    ],
    "name": "getTotalSquareSqrtSum",
    "outputs": [{ "internalType": "uint256", "name": "", "type": "uint256" }],
    "stateMutability": "view",
    "type": "function"
  },
  {
    "inputs": [
      { "internalType": "bytes32", "name": "role", "type": "bytes32" },
      { "internalType": "address", "name": "account", "type": "address" }
    ],
    "name": "grantRole",
    "outputs": [],
    "stateMutability": "nonpayable",
    "type": "function"
  },
  {
    "inputs": [
      { "internalType": "bytes32", "name": "role", "type": "bytes32" },
      { "internalType": "address", "name": "account", "type": "address" }
    ],
    "name": "hasRole",
    "outputs": [{ "internalType": "bool", "name": "", "type": "bool" }],
    "stateMutability": "view",
    "type": "function"
  },
  {
    "inputs": [
      { "internalType": "address", "name": "_owner", "type": "address" },
      {
        "internalType": "uint256",
        "name": "_MINIMUM_AMOUNT",
        "type": "uint256"
      }
    ],
    "name": "initialize",
    "outputs": [],
    "stateMutability": "nonpayable",
    "type": "function"
  },
  {
    "inputs": [],
    "name": "owner",
    "outputs": [{ "internalType": "address", "name": "", "type": "address" }],
    "stateMutability": "view",
    "type": "function"
  },
  {
    "inputs": [
      { "internalType": "string", "name": "_content", "type": "string" }
    ],
    "name": "postArticle",
    "outputs": [],
    "stateMutability": "nonpayable",
    "type": "function"
  },
  {
    "inputs": [
      { "internalType": "address", "name": "_admin", "type": "address" }
    ],
    "name": "removeAdmin",
    "outputs": [],
    "stateMutability": "nonpayable",
    "type": "function"
  },
  {
    "inputs": [],
    "name": "renounceOwnership",
    "outputs": [],
    "stateMutability": "nonpayable",
    "type": "function"
  },
  {
    "inputs": [
      { "internalType": "bytes32", "name": "role", "type": "bytes32" },
      {
        "internalType": "address",
        "name": "callerConfirmation",
        "type": "address"
      }
    ],
    "name": "renounceRole",
    "outputs": [],
    "stateMutability": "nonpayable",
    "type": "function"
  },
  {
    "inputs": [
      { "internalType": "bytes32", "name": "role", "type": "bytes32" },
      { "internalType": "address", "name": "account", "type": "address" }
    ],
    "name": "revokeRole",
    "outputs": [],
    "stateMutability": "nonpayable",
    "type": "function"
  },
  {
    "inputs": [
      { "internalType": "bytes4", "name": "interfaceId", "type": "bytes4" }
    ],
    "name": "supportsInterface",
    "outputs": [{ "internalType": "bool", "name": "", "type": "bool" }],
    "stateMutability": "view",
    "type": "function"
  },
  {
    "inputs": [
      { "internalType": "address", "name": "newOwner", "type": "address" }
    ],
    "name": "transferOwnership",
    "outputs": [],
    "stateMutability": "nonpayable",
    "type": "function"
  },
  {
    "inputs": [
      { "internalType": "uint256", "name": "_articleId", "type": "uint256" },
      { "internalType": "string", "name": "_content", "type": "string" }
    ],
    "name": "updateArticle",
    "outputs": [],
    "stateMutability": "nonpayable",
    "type": "function"
  }
]
